timestampedmodel/__init__.py
timestampedmodel/models.py
django_timestampedmodel-0.1.0.dist-info/LICENSE
django_timestampedmodel-0.1.0.dist-info/METADATA
django_timestampedmodel-0.1.0.dist-info/WHEEL
django_timestampedmodel-0.1.0.dist-info/top_level.txt
django_timestampedmodel-0.1.0.dist-info/RECORD
